glitch_forge/__init__.py
glitch_forge/_version.py
glitch_forge/example.py
glitch_forge/glitcher.py
glitch_forge/parameter.py
glitch_forge/ui.py
glitch_forge-1.0.2.dist-info/LICENSE
glitch_forge-1.0.2.dist-info/METADATA
glitch_forge-1.0.2.dist-info/WHEEL
glitch_forge-1.0.2.dist-info/top_level.txt
glitch_forge-1.0.2.dist-info/RECORD
