Metadata-Version: 2.2
Name: glitch_forge
Version: 1.0.2
Summary: Auto-generate PyQt6 GUIs from class parameters for quick tools and prototyping.
Author: Lukas Ukelis
Author-email: Lukas Ukelis <lukasukelis@gmail.com>
Project-URL: Homepage, https://github.com/LukasUkelis/GlitchForge
Project-URL: Issues, https://github.com/LukasUkelis/GlitchForge/issues
Classifier: Programming Language :: Python :: 3
Classifier: Operating System :: OS Independent
Requires-Python: >=3.10
License-File: LICENSE
Requires-Dist: PyQt6>=6.8.1
Dynamic: author
Dynamic: requires-python
